{
  "data": {
    "article": {},
    "attachments": {
      "media_keys": [
        "7_1825093978380722176"
      ]
    },
    "author_id": "1495662254544789506",
    "conversation_id": "1825094999647691076",
    "created_at": "2024-08-18T08:58:51.000Z",
    "edit_controls": {
      "editable_until": "2024-08-18T09:58:51.000Z",
      "edits_remaining": 5,
      "is_edit_eligible": true
    },
    "edit_history_tweet_ids": [
      "1825094999647691076"
    ],
    "entities": {
      "urls": [
        {
          "display_url": "pic.x.com/fvjdpgll7r",
          "end": 26,
          "expanded_url": "https://twitter.com/Aloevce/status/1825094999647691076/video/1",
          "media_key": "7_1825093978380722176",
          "start": 3,
          "url": "https://t.co/FVJDPgll7r"
        }
      ]
    },
    "geo": {},
    "id": "1825094999647691076",
    "lang": "zh",
    "possibly_sensitive": false,
    "public_metrics": {
      "bookmark_count": 0,
      "impression_count": 0,
      "like_count": 0,
      "quote_count": 0,
      "reply_count": 0,
      "retweet_count": 0
    },
    "reply_settings": "everyone",
    "text": "幽默 https://t.co/FVJDPgll7r"
  },
  "includes": {
    "media": [
      {
        "duration_ms": 4643,
        "height": 1280,
        "media_key": "7_1825093978380722176",
        "preview_image_url": "https://pbs.twimg.com/ext_tw_video_thumb/1825093978380722176/pu/img/tcF7axXbi6O7aOsO.jpg",
        "public_metrics": {
          "view_count": 0
        },
        "type": "video",
        "variants": [
          {
            "bit_rate": 632000,
            "content_type": "video/mp4",
            "url": "https://video.twimg.com/ext_tw_video/1825093978380722176/pu/vid/avc1/320x568/1VAuyAJWFxuT73-A.mp4?tag=12"
          },
          {
            "bit_rate": 950000,
            "content_type": "video/mp4",
            "url": "https://video.twimg.com/ext_tw_video/1825093978380722176/pu/vid/avc1/480x852/N7YLTb3q2eEEjgDQ.mp4?tag=12"
          },
          {
            "bit_rate": 2176000,
            "content_type": "video/mp4",
            "url": "https://video.twimg.com/ext_tw_video/1825093978380722176/pu/vid/avc1/720x1280/un4kyvXiV1V-gH8p.mp4?tag=12"
          },
          {
            "content_type": "application/x-mpegURL",
            "url": "https://video.twimg.com/ext_tw_video/1825093978380722176/pu/pl/VcUx1oH4TFXeUled.m3u8?tag=12"
          }
        ],
        "width": 720
      }
    ],
    "tweets": [
      {
        "article": {},
        "attachments": {
          "media_keys": [
            "7_1825093978380722176"
          ]
        },
        "author_id": "1495662254544789506",
        "conversation_id": "1825094999647691076",
        "created_at": "2024-08-18T08:58:51.000Z",
        "edit_controls": {
          "editable_until": "2024-08-18T09:58:51.000Z",
          "edits_remaining": 5,
          "is_edit_eligible": true
        },
        "edit_history_tweet_ids": [
          "1825094999647691076"
        ],
        "entities": {
          "urls": [
            {
              "display_url": "pic.x.com/fvjdpgll7r",
              "end": 26,
              "expanded_url": "https://twitter.com/Aloevce/status/1825094999647691076/video/1",
              "media_key": "7_1825093978380722176",
              "start": 3,
              "url": "https://t.co/FVJDPgll7r"
            }
          ]
        },
        "geo": {},
        "id": "1825094999647691076",
        "lang": "zh",
        "possibly_sensitive": false,
        "public_metrics": {
          "bookmark_count": 0,
          "impression_count": 0,
          "like_count": 0,
          "quote_count": 0,
          "reply_count": 0,
          "retweet_count": 0
        },
        "reply_settings": "everyone",
        "text": "幽默 https://t.co/FVJDPgll7r"
      }
    ],
    "users": [
      {
        "created_at": "2022-02-21T07:30:52.000Z",
        "description": "加速器🚀https://t.co/fWLEBLlyzt",
        "entities": {
          "description": {
            "urls": [
              {
                "display_url": "wwwwwl.sogood9.com/#/register?cod…",
                "end": 27,
                "expanded_url": "https://wwwwwl.sogood9.com/#/register?code=xtJc89Oz",
                "start": 4,
                "url": "https://t.co/fWLEBLlyzt"
              }
            ]
          }
        },
        "id": "1495662254544789506",
        "name": "厕所质检员",
        "pinned_tweet_id": "1822890228509532495",
        "profile_image_url": "https://pbs.twimg.com/profile_images/1806285347472523264/pJqCwqIH_normal.jpg",
        "protected": false,
        "public_metrics": {
          "followers_count": 17901,
          "following_count": 2227,
          "like_count": 52530,
          "listed_count": 22,
          "tweet_count": 18414
        },
        "username": "Aloevce",
        "verified": false
      }
    ]
  }
}