{
  "data": {
    "article": {},
    "attachments": {},
    "author_id": "1495662254544789506",
    "conversation_id": "1851268416088543631",
    "created_at": "2024-10-29T18:47:32.000Z",
    "edit_controls": {
      "editable_until": "2024-10-29T19:47:32.000Z",
      "edits_remaining": 5,
      "is_edit_eligible": false
    },
    "edit_history_tweet_ids": [
      "1851335073615757414"
    ],
    "entities": {
      "mentions": [
        {
          "end": 15,
          "id": "783159421555867648",
          "start": 0,
          "username": "Amenindeepmind"
        }
      ]
    },
    "geo": {},
    "id": "1851335073615757414",
    "in_reply_to_user_id": "783159421555867648",
    "lang": "zh",
    "possibly_sensitive": false,
    "public_metrics": {
      "bookmark_count": 0,
      "impression_count": 0,
      "like_count": 0,
      "quote_count": 0,
      "reply_count": 0,
      "retweet_count": 0
    },
    "referenced_tweets": [
      {
        "id": "1851334776449613849",
        "type": "replied_to"
      }
    ],
    "reply_settings": "everyone",
    "text": "@Amenindeepmind 为了ip啊啊啊"
  },
  "includes": {
    "tweets": [
      {
        "article": {},
        "attachments": {},
        "author_id": "1495662254544789506",
        "conversation_id": "1851268416088543631",
        "created_at": "2024-10-29T18:47:32.000Z",
        "edit_controls": {
          "editable_until": "2024-10-29T19:47:32.000Z",
          "edits_remaining": 5,
          "is_edit_eligible": false
        },
        "edit_history_tweet_ids": [
          "1851335073615757414"
        ],
        "entities": {
          "mentions": [
            {
              "end": 15,
              "id": "783159421555867648",
              "start": 0,
              "username": "Amenindeepmind"
            }
          ]
        },
        "geo": {},
        "id": "1851335073615757414",
        "in_reply_to_user_id": "783159421555867648",
        "lang": "zh",
        "possibly_sensitive": false,
        "public_metrics": {
          "bookmark_count": 0,
          "impression_count": 0,
          "like_count": 0,
          "quote_count": 0,
          "reply_count": 0,
          "retweet_count": 0
        },
        "referenced_tweets": [
          {
            "id": "1851334776449613849",
            "type": "replied_to"
          }
        ],
        "reply_settings": "everyone",
        "text": "@Amenindeepmind 为了ip啊啊啊"
      },
      {
        "article": {},
        "attachments": {},
        "author_id": "783159421555867648",
        "context_annotations": [
          {
            "domain": {
              "description": "Top level entities that describe a Brands industry",
              "id": "45",
              "name": "Brand Vertical"
            },
            "entity": {
              "id": "781974597310615553",
              "name": "Entertainment"
            }
          },
          {
            "domain": {
              "description": "Entity Service top level domain, every item that is in Entity Service should be in this domain",
              "id": "30",
              "name": "Entities [Entity Service]"
            },
            "entity": {
              "id": "781974597218340864",
              "name": "Video Games - Entertainment"
            }
          },
          {
            "domain": {
              "description": "Categories within Brand Verticals that narrow down the scope of Brands",
              "id": "46",
              "name": "Business Taxonomy"
            },
            "entity": {
              "description": "Brands, companies, advertisers and every non-person handle with the profit intent related to movies, music, television, franchises, venues, theme parks, toys, tourism, hotels",
              "id": "1557696802391859201",
              "name": "Entertainment & Leisure Business"
            }
          },
          {
            "domain": {
              "description": "Categories within Brand Verticals that narrow down the scope of Brands",
              "id": "46",
              "name": "Business Taxonomy"
            },
            "entity": {
              "description": "Brands, companies, advertisers and every non-person handle with the profit intent related to offline and online games such as gaming consoles, tabletop games, video game publishers",
              "id": "1557696940178935808",
              "name": "Gaming Business"
            }
          },
          {
            "domain": {
              "description": "Franchises which span multiple forms of media like 'Harry Potter'",
              "id": "130",
              "name": "Multimedia Franchise"
            },
            "entity": {
              "description": "This entity includes all conversation about the franchise, as well as any individual installments in the series, if applicable. **NOTE: Annotations redirected to domain 130 ONLY on 8/7/18.",
              "id": "10045599546",
              "name": "Pokémon"
            }
          },
          {
            "domain": {
              "description": "A taxonomy of user interests. ",
              "id": "131",
              "name": "Unified Twitter Taxonomy"
            },
            "entity": {
              "description": "This entity includes all conversation about the franchise, as well as any individual installments in the series, if applicable. **NOTE: Annotations redirected to domain 130 ONLY on 8/7/18.",
              "id": "10045599546",
              "name": "Pokémon"
            }
          },
          {
            "domain": {
              "description": "A taxonomy of user interests. ",
              "id": "131",
              "name": "Unified Twitter Taxonomy"
            },
            "entity": {
              "id": "839544274442051584",
              "name": "Entertainment"
            }
          },
          {
            "domain": {
              "description": "A taxonomy of user interests. ",
              "id": "131",
              "name": "Unified Twitter Taxonomy"
            },
            "entity": {
              "description": "Gaming",
              "id": "847527650667094017",
              "name": "Gaming"
            }
          },
          {
            "domain": {
              "description": "A taxonomy of user interests. ",
              "id": "131",
              "name": "Unified Twitter Taxonomy"
            },
            "entity": {
              "id": "1070028159964262400",
              "name": "Video games"
            }
          }
        ],
        "conversation_id": "1851268416088543631",
        "created_at": "2024-10-29T18:46:21.000Z",
        "edit_controls": {
          "editable_until": "2024-10-29T19:46:21.000Z",
          "edits_remaining": 5,
          "is_edit_eligible": false
        },
        "edit_history_tweet_ids": [
          "1851334776449613849"
        ],
        "entities": {
          "mentions": [
            {
              "end": 8,
              "id": "1495662254544789506",
              "start": 0,
              "username": "Aloevce"
            }
          ]
        },
        "geo": {},
        "id": "1851334776449613849",
        "in_reply_to_user_id": "1495662254544789506",
        "lang": "zh",
        "possibly_sensitive": false,
        "public_metrics": {
          "bookmark_count": 0,
          "impression_count": 0,
          "like_count": 1,
          "quote_count": 0,
          "reply_count": 1,
          "retweet_count": 0
        },
        "referenced_tweets": [
          {
            "id": "1851268416088543631",
            "type": "replied_to"
          }
        ],
        "reply_settings": "everyone",
        "text": "@Aloevce 宝可梦大集结不是很好玩儿、、"
      }
    ],
    "users": [
      {
        "created_at": "2022-02-21T07:30:52.000Z",
        "description": "神人",
        "id": "1495662254544789506",
        "name": "刻舟求剑",
        "pinned_tweet_id": "1851276636152352989",
        "profile_image_url": "https://pbs.twimg.com/profile_images/1831653051679096832/5KzaPtOF_normal.jpg",
        "protected": false,
        "public_metrics": {
          "followers_count": 17748,
          "following_count": 2239,
          "like_count": 53046,
          "listed_count": 23,
          "tweet_count": 19180
        },
        "username": "Aloevce",
        "verified": false
      },
      {
        "created_at": "2016-10-04T04:18:51.000Z",
        "description": "祝您生活愉快",
        "id": "783159421555867648",
        "location": "United States",
        "name": "UcConnKk",
        "profile_image_url": "https://pbs.twimg.com/profile_images/1834376044947636225/IRvT5a3h_normal.jpg",
        "protected": false,
        "public_metrics": {
          "followers_count": 107,
          "following_count": 774,
          "like_count": 4255,
          "listed_count": 0,
          "tweet_count": 1084
        },
        "username": "Amenindeepmind",
        "verified": false
      }
    ]
  }
}