{
  "data": {
    "article": {},
    "attachments": {},
    "author_id": "1495662254544789506",
    "conversation_id": "2069668031207247962",
    "created_at": "2026-06-24T06:24:45.000Z",
    "edit_controls": {
      "editable_until": "2026-06-24T07:24:45.000Z",
      "edits_remaining": 5,
      "is_edit_eligible": true
    },
    "edit_history_tweet_ids": [
      "2069668031207247962"
    ],
    "entities": {
      "urls": [
        {
          "display_url": "x.com/Aloevce/status…",
          "end": 43,
          "expanded_url": "https://twitter.com/Aloevce/status/2069602986813165713",
          "start": 20,
          "url": "https://t.co/EeshUsq6Xv"
        }
      ]
    },
    "geo": {},
    "id": "2069668031207247962",
    "lang": "zh",
    "note_tweet": {
      "entities": {}
    },
    "possibly_sensitive": false,
    "public_metrics": {
      "bookmark_count": 0,
      "impression_count": 0,
      "like_count": 0,
      "quote_count": 0,
      "reply_count": 0,
      "retweet_count": 0
    },
    "referenced_tweets": [
      {
        "id": "2069602986813165713",
        "type": "quoted"
      }
    ],
    "reply_settings": "everyone",
    "text": "最后我打个电话给对象哥他爸叫过来才消停 https://t.co/EeshUsq6Xv"
  },
  "includes": {
    "tweets": [
      {
        "article": {},
        "attachments": {},
        "author_id": "1495662254544789506",
        "conversation_id": "2069668031207247962",
        "created_at": "2026-06-24T06:24:45.000Z",
        "edit_controls": {
          "editable_until": "2026-06-24T07:24:45.000Z",
          "edits_remaining": 5,
          "is_edit_eligible": true
        },
        "edit_history_tweet_ids": [
          "2069668031207247962"
        ],
        "entities": {
          "urls": [
            {
              "display_url": "x.com/Aloevce/status…",
              "end": 43,
              "expanded_url": "https://twitter.com/Aloevce/status/2069602986813165713",
              "start": 20,
              "url": "https://t.co/EeshUsq6Xv"
            }
          ]
        },
        "geo": {},
        "id": "2069668031207247962",
        "lang": "zh",
        "note_tweet": {
          "entities": {}
        },
        "possibly_sensitive": false,
        "public_metrics": {
          "bookmark_count": 0,
          "impression_count": 0,
          "like_count": 0,
          "quote_count": 0,
          "reply_count": 0,
          "retweet_count": 0
        },
        "referenced_tweets": [
          {
            "id": "2069602986813165713",
            "type": "quoted"
          }
        ],
        "reply_settings": "everyone",
        "text": "最后我打个电话给对象哥他爸叫过来才消停 https://t.co/EeshUsq6Xv"
      },
      {
        "article": {},
        "attachments": {},
        "author_id": "1495662254544789506",
        "conversation_id": "2069602986813165713",
        "created_at": "2026-06-24T02:06:18.000Z",
        "edit_controls": {
          "editable_until": "2026-06-24T03:06:18.000Z",
          "edits_remaining": 5,
          "is_edit_eligible": true
        },
        "edit_history_tweet_ids": [
          "2069602986813165713"
        ],
        "entities": {},
        "geo": {},
        "id": "2069602986813165713",
        "lang": "zh",
        "note_tweet": {
          "entities": {}
        },
        "possibly_sensitive": false,
        "public_metrics": {
          "bookmark_count": 0,
          "impression_count": 301,
          "like_count": 14,
          "quote_count": 1,
          "reply_count": 3,
          "retweet_count": 0
        },
        "reply_settings": "everyone",
        "text": "对象哥耍酒疯吵架又摔东西又骂又赶我走的 我无助得都不知道该干啥"
      }
    ],
    "users": [
      {
        "created_at": "2022-02-21T07:30:52.000Z",
        "description": "呆呆兽从小就很可爱",
        "id": "1495662254544789506",
        "location": "闪焰王牌official",
        "name": "刻舟求剑",
        "pinned_tweet_id": "2058652551415763284",
        "profile_image_url": "https://pbs.twimg.com/profile_images/2056492489151066112/QqCOsSSQ_normal.jpg",
        "protected": false,
        "public_metrics": {
          "followers_count": 18089,
          "following_count": 1959,
          "like_count": 56347,
          "listed_count": 23,
          "media_count": 6829,
          "tweet_count": 24022
        },
        "url": "",
        "username": "Aloevce",
        "verified": false
      }
    ]
  }
}